dictionary_cli/__init__.py
dictionary_cli/main.py
dictionary_cli-0.0.3.dist-info/licenses/LICENSE
dictionary_cli-0.0.3.dist-info/METADATA
dictionary_cli-0.0.3.dist-info/WHEEL
dictionary_cli-0.0.3.dist-info/entry_points.txt
dictionary_cli-0.0.3.dist-info/top_level.txt
dictionary_cli-0.0.3.dist-info/RECORD
