Metadata-Version: 2.4
Name: dictionary-cli
Version: 0.0.3
Summary: A simple CLI dictionary for definitions, synonyms, and antonyms from dictionaryapi.dev
Author-email: Dekoder-py <dekod3r.py@gmail.com>
License: MIT License
Project-URL: Homepage, https://summer.hackclub.com/projects/11298
Project-URL: Source, https://github.com/Dekoder-py/Dictionary
Requires-Python: >=3.8
License-File: LICENSE
Requires-Dist: requests>=2.0.0
Requires-Dist: rich>=14.0.0
Dynamic: license-file
